{"news":[{"id":2,"title":"news 10","desc":"desc"},{"id":3,"title":"news 10","desc":"desc"},{"id":4,"title":"news 10","desc":"desc"},{"id":5,"title":"news 10","desc":"desc"},{"id":6,"title":"news 11","desc":"desc"},{"id":7,"title":"news 12","desc":"desc"},{"id":8,"title":"news 12","desc":"desc"},{"id":9,"title":"news 12","desc":"desc"}],"articles":[{"id":2,"title":"Article","desc":"Desc"},{"id":3,"title":"Article","desc":"Desc"},{"id":4,"title":"Article","desc":"Desc"},{"id":5,"title":"Article","desc":"Desc"},{"id":6,"title":"Article","desc":"Desc"},{"id":7,"title":"Article","desc":"Desc"},{"id":8,"title":"Article","desc":"Desc"},{"id":9,"title":"Article","desc":"Desc"},{"id":10,"title":"Article","desc":"Desc"}],"users":[{"name":"user","email":"user@mail.com","password":"$2b$10$JBdmDdHMDrOax4WM/F9PP.VB8NtOlAPMxVvoYxF2iUpsdzH6ShRM6"},{"id":1,"name":"user","email":"user@mail.com","password":"$2b$10$N8q3bct1kk9yaS7DrC4kP.DlR5F4e3qX/l.3f8c5b93sXQLaR6FZK"},{"id":2,"name":"user","email":"user@mail.com","password":"$2b$10$v/MN4iO8U.IWEigmUnGGDeqZVbJcQ537yhQuOlYkVp5h8/6Bhyf.K"}]}